cxyx_tools/__init__.py
cxyx_tools/core/__init__.py
cxyx_tools/core/gradient.py
cxyx_tools/core/variable.py
cxyx_tools/utils/__init__.py
cxyx_tools/utils/method_wrapper.py
cxyxtools-0.0.0.8.dist-info/METADATA
cxyxtools-0.0.0.8.dist-info/WHEEL
cxyxtools-0.0.0.8.dist-info/top_level.txt
cxyxtools-0.0.0.8.dist-info/RECORD
